MANIFEST.in
README.rst
requirements.txt
setup.py
UISoup.egg-info/PKG-INFO
UISoup.egg-info/SOURCES.txt
UISoup.egg-info/dependency_links.txt
UISoup.egg-info/entry_points.txt
UISoup.egg-info/not-zip-safe
UISoup.egg-info/requires.txt
UISoup.egg-info/top_level.txt
uisoup/__init__.py
uisoup/ui_inspector.py
uisoup/interfaces/__init__.py
uisoup/interfaces/i_element.py
uisoup/interfaces/i_keyboard.py
uisoup/interfaces/i_mouse.py
uisoup/interfaces/i_soup.py
uisoup/mac_soup/__init__.py
uisoup/mac_soup/element.py
uisoup/mac_soup/keyboard.py
uisoup/mac_soup/mac_soup.py
uisoup/mac_soup/mouse.py
uisoup/utils/__init__.py
uisoup/utils/common.py
uisoup/utils/mac_utils.py
uisoup/utils/win_utils.py
uisoup/win_soup/__init__.py
uisoup/win_soup/element.py
uisoup/win_soup/keyboard.py
uisoup/win_soup/mouse.py
uisoup/win_soup/win_soup.py