Metadata-Version: 1.0
Name: UISoup
Version: 2.5.7
Summary: Cross Platform GUI Test Automation tool.
Home-page: UNKNOWN
Author: Max Beloborodko
Author-email: f1ashhimself@gmail.com
License: UNKNOWN
Platform: UNKNOWN
